plain/dev/AGENTS.md
plain/dev/CHANGELOG.md
plain/dev/README.md
plain/dev/__init__.py
plain/dev/alias.py
plain/dev/cli.py
plain/dev/core.py
plain/dev/debug.py
plain/dev/default_settings.py
plain/dev/entrypoints.py
plain/dev/mkcert.py
plain/dev/pdb.py
plain/dev/process.py
plain/dev/services.py
plain/dev/utils.py
plain/dev/contribute/README.md
plain/dev/contribute/__init__.py
plain/dev/contribute/cli.py
plain/dev/poncho/__init__.py
plain/dev/poncho/color.py
plain/dev/poncho/compat.py
plain/dev/poncho/manager.py
plain/dev/poncho/printer.py
plain/dev/poncho/process.py
plain/dev/precommit/__init__.py
plain/dev/precommit/cli.py
plain_dev-0.49.1.dist-info/METADATA
plain_dev-0.49.1.dist-info/WHEEL
plain_dev-0.49.1.dist-info/entry_points.txt
plain_dev-0.49.1.dist-info/licenses/LICENSE
plain_dev-0.49.1.dist-info/RECORD
