Metadata-Version: 2.4
Name: plain.dev
Version: 0.49.1
Summary: A single command that runs everything you need for local development.
Author-email: Dave Gaeddert <dave.gaeddert@dropseed.dev>
License-Expression: BSD-3-Clause
License-File: LICENSE
Requires-Python: >=3.13
Requires-Dist: click>=8.0.0
Requires-Dist: inotify
Requires-Dist: plain<1.0.0
Requires-Dist: python-dotenv~=1.0.0
Requires-Dist: requests>=2.0.0
Requires-Dist: rich
